[
	{
		"name": "Hm_lpvt_0c0e9d9b1e7d617b3e6842e85b9fb068",
		"value": "1642159117",
		"domain": ".jianshu.com",
		"path": "/",
		"expires": -1,
		"size": 50,
		"httpOnly": false,
		"secure": false,
		"session": true,
		"sameParty": false,
		"sourceScheme": "Secure",
		"sourcePort": 443
	},
	{
		"name": "_m7e_session_core",
		"value": "27271c0ea8c4c0ad133324504a9986cb",
		"domain": ".jianshu.com",
		"path": "/",
		"expires": 1642180717.794234,
		"size": 49,
		"httpOnly": true,
		"secure": true,
		"session": false,
		"sameParty": false,
		"sourceScheme": "Secure",
		"sourcePort": 443
	},
	{
		"name": "_gat",
		"value": "1",
		"domain": ".jianshu.com",
		"path": "/",
		"expires": -1,
		"size": 5,
		"httpOnly": false,
		"secure": false,
		"session": true,
		"sameParty": false,
		"sourceScheme": "NonSecure",
		"sourcePort": 80
	},
	{
		"name": "Hm_lvt_0c0e9d9b1e7d617b3e6842e85b9fb068",
		"value": "1641183640,1641289046,1641296308,1642158733",
		"domain": ".jianshu.com",
		"path": "/",
		"expires": 1673695117,
		"size": 82,
		"httpOnly": false,
		"secure": false,
		"session": false,
		"sameParty": false,
		"sourceScheme": "Secure",
		"sourcePort": 443
	},
	{
		"name": "_ga",
		"value": "GA1.2.1255438408.1640425603",
		"domain": ".jianshu.com",
		"path": "/",
		"expires": -1,
		"size": 30,
		"httpOnly": false,
		"secure": false,
		"session": true,
		"sameParty": false,
		"sourceScheme": "NonSecure",
		"sourcePort": 80
	},
	{
		"name": "CNZZDATA1279807957",
		"value": "1124342939-1641167353-https%253A%252F%252Fwww.google.com%252F%7C1642151511",
		"domain": "www.jianshu.com",
		"path": "/",
		"expires": 1657883917,
		"size": 92,
		"httpOnly": false,
		"secure": false,
		"session": false,
		"sameParty": false,
		"sourceScheme": "Secure",
		"sourcePort": 443
	},
	{
		"name": "UM_distinctid",
		"value": "17e1dd01248ca2-080585f9cb38f1-4303066-144000-17e1dd01249c09",
		"domain": ".jianshu.com",
		"path": "/",
		"expires": -1,
		"size": 72,
		"httpOnly": false,
		"secure": false,
		"session": true,
		"sameParty": false,
		"sourceScheme": "NonSecure",
		"sourcePort": 80
	},
	{
		"name": "web_login_version",
		"value": "MTY0MjE1NTEzMA%3D%3D--a7478a5e858ef27f002c58973ddf8769a5aac831",
		"domain": ".jianshu.com",
		"path": "/",
		"expires": -1,
		"size": 79,
		"httpOnly": true,
		"secure": false,
		"session": true,
		"sameParty": false,
		"sourceScheme": "NonSecure",
		"sourcePort": 80
	},
	{
		"name": "_gid",
		"value": "GA1.2.914635442.1642154692",
		"domain": ".jianshu.com",
		"path": "/",
		"expires": -1,
		"size": 30,
		"httpOnly": false,
		"secure": false,
		"session": true,
		"sameParty": false,
		"sourceScheme": "NonSecure",
		"sourcePort": 80
	},
	{
		"name": "default_font",
		"value": "font2",
		"domain": "www.jianshu.com",
		"path": "/",
		"expires": -1,
		"size": 17,
		"httpOnly": false,
		"secure": false,
		"session": true,
		"sameParty": false,
		"sourceScheme": "NonSecure",
		"sourcePort": 80
	},
	{
		"name": "locale",
		"value": "zh-CN",
		"domain": "www.jianshu.com",
		"path": "/",
		"expires": -1,
		"size": 11,
		"httpOnly": false,
		"secure": false,
		"session": true,
		"sameParty": false,
		"sourceScheme": "Secure",
		"sourcePort": 443
	},
	{
		"name": "read_mode",
		"value": "day",
		"domain": "www.jianshu.com",
		"path": "/",
		"expires": -1,
		"size": 12,
		"httpOnly": false,
		"secure": false,
		"session": true,
		"sameParty": false,
		"sourceScheme": "NonSecure",
		"sourcePort": 80
	},
	{
		"name": "sensorsdata2015jssdkcross",
		"value": "%7B%22distinct_id%22%3A%2227588158%22%2C%22first_id%22%3A%2217df0fc4073694-00eeda0db583a8-4303066-1327104-17df0fc4074ed5%22%2C%22props%22%3A%7B%22%24latest_traffic_source_type%22%3A%22%E7%9B%B4%E6%8E%A5%E6%B5%81%E9%87%8F%22%2C%22%24latest_search_keyword%22%3A%22%E6%9C%AA%E5%8F%96%E5%88%B0%E5%80%BC_%E7%9B%B4%E6%8E%A5%E6%89%93%E5%BC%80%22%2C%22%24latest_referrer%22%3A%22%22%7D%2C%22%24device_id%22%3A%2217df0fc4073694-00eeda0db583a8-4303066-1327104-17df0fc4074ed5%22%7D",
		"domain": ".jianshu.com",
		"path": "/",
		"expires": 7949359117,
		"size": 495,
		"httpOnly": false,
		"secure": false,
		"session": false,
		"sameParty": false,
		"sourceScheme": "Secure",
		"sourcePort": 443
	}
]